respot/VERSION.txt
respot/__init__.py
respot/about.py
respot/gui.py
respot/img/no-music.png
respotgui-0.1.71.dist-info/LICENSE
respotgui-0.1.71.dist-info/METADATA
respotgui-0.1.71.dist-info/WHEEL
respotgui-0.1.71.dist-info/entry_points.txt
respotgui-0.1.71.dist-info/top_level.txt
respotgui-0.1.71.dist-info/RECORD
