Metadata-Version: 2.1
Name: respotgui
Version: 0.1.71
Summary: A frontend for the respot-java Spotify client
Home-page: https://github.com/digfish/respotgui
Author: digfish
Author-email: digfish@digfish.org
License: Apache License 2.0
Classifier: Development Status :: 2 - Pre-Alpha
Classifier: Environment :: Win32 (MS Windows)
Classifier: Programming Language :: Python :: 3
Classifier: License :: OSI Approved :: Apache Software License
Classifier: Operating System :: Microsoft :: Windows
License-File: LICENSE
Requires-Dist: ordered-set (==4.1.0)
Requires-Dist: Pillow (==9.3.0)
Requires-Dist: pycaw (==20220416)
Requires-Dist: pynput (==1.7.6)
Requires-Dist: PySimpleGUI (==4.60.4)
Requires-Dist: python-dotenv (==0.21.0)
Requires-Dist: requests (==2.28.1)
Requires-Dist: setuptools (==65.3.0)
Requires-Dist: versioneer (==0.26)
Requires-Dist: websocket-client (==1.4.2)
